ebm_utils/__init__.py
ebm_utils/fit.py
ebm_utils/load.py
ebm_utils/analysis/__init__.py
ebm_utils/analysis/changepoints.py
ebm_utils/analysis/embeddings.py
ebm_utils/analysis/importance.py
ebm_utils/analysis/marginalize.py
ebm_utils/analysis/plot_utils.py
ebm_utils/analysis/purify_utils.py
ebm_utils/preprocessing/__init__.py
ebm_utils/preprocessing/preprocessing_utils.py
ebm_utils-0.0.2.dist-info/LICENSE
ebm_utils-0.0.2.dist-info/METADATA
ebm_utils-0.0.2.dist-info/WHEEL
ebm_utils-0.0.2.dist-info/top_level.txt
ebm_utils-0.0.2.dist-info/RECORD
